PyFT8/FT8_crc.py
PyFT8/FT8_encoder.py
PyFT8/FT8_unpack.py
PyFT8/PyFT8_cli.py
PyFT8/__init__.py
PyFT8/audio.py
PyFT8/cycle_manager.py
PyFT8/ldpc.py
PyFT8/osd.py
PyFT8/sigspecs.py
pyft8-1.0.5.dist-info/licenses/LICENSE
pyft8-1.0.5.dist-info/METADATA
pyft8-1.0.5.dist-info/WHEEL
pyft8-1.0.5.dist-info/entry_points.txt
pyft8-1.0.5.dist-info/top_level.txt
pyft8-1.0.5.dist-info/RECORD
