Metadata-Version: 2.4
Name: PyFT8
Version: 1.0.5
Summary: FT8 Decoding and Encoding in Python with test/loopback code
Author-email: G1OJS <g1ojs@yahoo.com>
License-Expression: GPL-3.0-or-later
Project-URL: Homepage, https://github.com/G1OJS/PyFT8
Project-URL: Issues, https://github.com/G1OJS/PyFT8/issues
Keywords: ham radio,radio,FT8,LDPC,CPMFSK
Classifier: Programming Language :: Python :: 3
Classifier: Operating System :: OS Independent
Requires-Python: >=3.8
License-File: LICENSE
Requires-Dist: numpy>=1.24.0
Requires-Dist: matplotlib
Requires-Dist: pyaudio
Dynamic: license-file
